isf_pandas_msgpack/__init__.py
isf_pandas_msgpack/_move.cp38-win_amd64.pyd
isf_pandas_msgpack/_version.py
isf_pandas_msgpack/move.c
isf_pandas_msgpack/packers.py
isf_pandas_msgpack/pandas_compat.py
isf_pandas_msgpack/includes/pack.h
isf_pandas_msgpack/includes/pack_template.h
isf_pandas_msgpack/includes/sysdep.h
isf_pandas_msgpack/includes/unpack.h
isf_pandas_msgpack/includes/unpack_define.h
isf_pandas_msgpack/includes/unpack_template.h
isf_pandas_msgpack/msgpack/__init__.py
isf_pandas_msgpack/msgpack/_packer.cp38-win_amd64.pyd
isf_pandas_msgpack/msgpack/_packer.pyx
isf_pandas_msgpack/msgpack/_unpacker.cp38-win_amd64.pyd
isf_pandas_msgpack/msgpack/_unpacker.pyx
isf_pandas_msgpack/msgpack/exceptions.py
isf_pandas_msgpack-0.4.0.dist-info/LICENSE.md
isf_pandas_msgpack-0.4.0.dist-info/METADATA
isf_pandas_msgpack-0.4.0.dist-info/WHEEL
isf_pandas_msgpack-0.4.0.dist-info/top_level.txt
isf_pandas_msgpack-0.4.0.dist-info/RECORD
