Metadata-Version: 2.1
Name: isf-pandas-msgpack
Version: 0.4.0
Summary: Pandas interface to msgpack - ISF patch
License: BSD-3-Clause
Classifier: Development Status :: 4 - Beta
Classifier: Environment :: Console
Classifier: Intended Audience :: Science/Research
Classifier: Operating System :: OS Independent
Classifier: Programming Language :: Python
Classifier: Programming Language :: Python :: 3.8
Classifier: Programming Language :: Python :: 3.9
Classifier: Programming Language :: Python :: 3.10
Classifier: Programming Language :: Python :: 3.11
Classifier: Programming Language :: Python :: 3.12
Classifier: Programming Language :: Python :: 3.13
Classifier: Topic :: Scientific/Engineering
Requires-Python: <3.14,>=3.8
License-File: LICENSE.md
Requires-Dist: pandas <3,>=1.1.0
